hera/__init__.py
hera/assembler.py
hera/checker.py
hera/config.py
hera/data.py
hera/debugger.py
hera/disassembler.py
hera/exceptions.py
hera/lexer.py
hera/loader.py
hera/main.py
hera/op.py
hera/parser.py
hera/preprocessor.py
hera/stdlib.py
hera/symtab.py
hera/typechecker.py
hera/utils.py
hera/vm.py
hera/debugger/__init__.py
hera/debugger/debugger.py
hera/debugger/minilanguage.py
hera/debugger/miniparser.py
hera/debugger/shell.py
test/__init__.py
test/test_assembler.py
test/test_cmd.py
test/test_config.py
test/test_debugger.py
test/test_disassembler.py
test/test_error.py
test/test_from_cs240.py
test/test_from_cs350.py
test/test_from_manual.py
test/test_include.py
test/test_integ_simple.py
test/test_integration.py
test/test_main.py
test/test_misc.py
test/test_parse_error.py
test/test_parser.py
test/test_preprocessor.py
test/test_symtab.py
test/test_typechecker.py
test/test_utils.py
test/test_vm.py
test/test_warning.py
test/utils.py
test/test_exec/__init__.py
test/test_exec/test_arithmetic_logic.py
test/test_exec/test_branch_call_return.py
test/test_exec/test_data_statements.py
test/test_exec/test_debug_ops.py
test/test_exec/test_flag.py
test/test_exec/test_interrupt.py
test/test_exec/test_load_store.py
test/test_exec/test_set_inc_dec.py
test/test_exec/test_shift.py
test/test_exec/utils.py
test/test_integration/__init__.py
test/test_integration/test_cs240.py
test/test_integration/test_error.py
test/test_integration/test_include.py
test/test_integration/test_manual.py
test/test_integration/test_simple.py
test/test_op/__init__.py
test/test_op/test_arithmetic_logic.py
test/test_op/test_branch_call_return.py
test/test_op/test_data_statements.py
test/test_op/test_debug_ops.py
test/test_op/test_debugging.py
test/test_op/test_flag.py
test/test_op/test_interrupt.py
test/test_op/test_load_store.py
test/test_op/test_misc.py
test/test_op/test_set_inc_dec.py
test/test_op/test_shift.py
test/test_unit/__init__.py
test/test_unit/test_checker.py
test/test_unit/test_conversion.py
hera_py-1.0.7.dist-info/LICENSE
hera_py-1.0.7.dist-info/METADATA
hera_py-1.0.7.dist-info/WHEEL
hera_py-1.0.7.dist-info/entry_points.txt
hera_py-1.0.7.dist-info/top_level.txt
hera_py-1.0.7.dist-info/RECORD
