Metadata-Version: 2.1
Name: hera-py
Version: 1.0.7
Summary: Interpreter for the Haverford Educational RISC Architecture (HERA) assembly language
Home-page: UNKNOWN
Author: Ian Fisher
Author-email: iafisher@fastmail.com
License: MIT
Project-URL: Source, https://github.com/iafisher/hera-py
Platform: UNKNOWN
Classifier: Programming Language :: Python :: 3
Classifier: License :: OSI Approved :: MIT License
Classifier: Natural Language :: English
Classifier: Topic :: Software Development :: Assemblers
